chiter/__init__.py
chiter/chiter.py
chiter/deferred_iterator.py
chiter/helpers.py
chiter/meta.py
chiter-1.0.0a2.dist-info/LICENSE
chiter-1.0.0a2.dist-info/WHEEL
chiter-1.0.0a2.dist-info/METADATA
chiter-1.0.0a2.dist-info/RECORD
