Metadata-Version: 2.1
Name: chiter
Version: 1.0.0a2
Summary: iterable as a chain
Home-page: https://github.com/nede1/chiter
License: MIT
Keywords: fluent interface,method chaining
Author: Yaroslav Bibaev
Author-email: yaroslav@gmx.com
Requires-Python: >=3.7,<4.0
Classifier: License :: OSI Approved :: MIT License
Classifier: Programming Language :: Python :: 3
Classifier: Programming Language :: Python :: 3.7
Project-URL: Repository, https://github.com/nede1/chiter
